README.rst
setup.py
TBCCpylinac.egg-info/PKG-INFO
TBCCpylinac.egg-info/SOURCES.txt
TBCCpylinac.egg-info/dependency_links.txt
TBCCpylinac.egg-info/requires.txt
TBCCpylinac.egg-info/top_level.txt
pylinac/__init__.py
pylinac/ct.py
pylinac/flatsym.py
pylinac/log_analyzer.py
pylinac/picketfence.py
pylinac/planar_imaging.py
pylinac/py_gui.py
pylinac/settings.py
pylinac/starshot.py
pylinac/vmat.py
pylinac/watcher.py
pylinac/watcher_config.yml
pylinac/winston_lutz.py
pylinac/calibration/__init__.py
pylinac/calibration/tg51.py
pylinac/calibration/trs398.py
pylinac/core/__init__.py
pylinac/core/decorators.py
pylinac/core/exceptions.py
pylinac/core/geometry.py
pylinac/core/image.py
pylinac/core/io.py
pylinac/core/mask.py
pylinac/core/mtf.py
pylinac/core/pdf.py
pylinac/core/profile.py
pylinac/core/roi.py
pylinac/core/typing.py
pylinac/core/utilities.py
pylinac/core/vmatIMAGE.py
pylinac/files/Pylinac Full cropped.png